[1,["aaL8evzX5JkYFcCx/8+CMw@f9941","d8x6fSd2FF+ZRa3ApBRVP5@f9941","ebdNcrRKZBpJtj1PB0eMk/@f9941","17UmVI5yVA2bztgDEXmYSK@6c48a","21I8oS049FpJW/2RjafafL@6c48a","20g1ukYUVPvKWKBRznAKo+@f9941","aer8Q30iNAJr4/DBlf6KOQ@f9941","21I8oS049FpJW/2RjafafL@f9941","ebqDAIgRJL4rq6nfi4bA4b@f9941","17UmVI5yVA2bztgDEXmYSK@f9941","bcUHb+6d1IhaZwPw3TJJ4/@f9941","aaL8evzX5JkYFcCx/8+CMw@6c48a","aer8Q30iNAJr4/DBlf6KOQ@6c48a","bcUHb+6d1IhaZwPw3TJJ4/@6c48a","d8x6fSd2FF+ZRa3ApBRVP5@6c48a","ebdNcrRKZBpJtj1PB0eMk/@6c48a","ebqDAIgRJL4rq6nfi4bA4b@6c48a"],["node","_spriteFrame","_textureSource","root","sfxProgressBar","sfxKnob","bgmProgressBar","bgmKnob","closeButtonNode","panelSpriteNode","data"],["cc.SpriteFrame",["cc.Node",["_name","_layer","_components","_prefab","_parent","_children","_lpos"],1,9,4,1,2,5],["cc.Sprite",["_sizeMode","_type","node","__prefab","_spriteFrame","_color"],1,1,4,6,5],["cc.Node",["_name","_layer","_parent","_components","_prefab","_lpos","_children"],1,1,12,4,5,2],["cc.UITransform",["node","__prefab","_contentSize","_anchorPoint"],3,1,4,5,5],["cc.Widget",["_alignFlags","_originalWidth","_originalHeight","_left","_right","_top","_bottom","node","__prefab"],-4,1,4],["cc.Button",["_transition","node","__prefab","clickEvents"],2,1,4,9],["cc.Prefab",["_name"],2],["cc.CompPrefabInfo",["fileId"],2],["97668z8Sv5GPp0DunWEXrPZ",["node","__prefab","panelSpriteNode","closeButtonNode","bgmKnob","bgmProgressBar","sfxKnob","sfxProgressBar"],3,1,4,1,1,1,1,1,1],["cc.PrefabInfo",["fileId","instance","targetOverrides","nestedPrefabInstanceRoots","root","asset"],-1,1,1],["cc.ClickEvent",["_componentId","handler","target"],1,1],["cc.Label",["_string","_actualFontSize","_fontSize","_lineHeight","_overflow","_isBold","_cacheMode","_enableOutline","node","__prefab","_outlineColor"],-5,1,4,5],["cc.ProgressBar",["_mode","_progress","node","__prefab","_barSprite"],1,1,4,1]],[[8,0,2],[10,0,1,2,3,4,5,5],[4,0,1,2,1],[1,0,1,4,2,3,6,3],[2,2,3,4,1],[1,0,1,4,5,2,3,3],[5,0,3,4,5,6,1,2,7,8,8],[3,0,1,2,6,3,4,5,3],[3,0,1,2,3,4,5,3],[4,0,1,2,3,1],[5,0,1,2,7,8,4],[2,1,0,2,3,4,3],[2,1,0,2,3,3],[13,0,1,2,3,4,3],[7,0,2],[1,0,1,5,2,3,3],[1,0,1,4,2,3,3],[1,0,1,4,5,2,3,6,3],[9,0,1,2,3,4,5,6,7,1],[2,0,2,3,4,2],[2,1,0,2,3,5,4,3],[6,1,2,1],[6,0,1,2,3,2],[11,0,1,2,3],[12,0,1,2,3,4,5,6,7,8,9,10,9]],[[[{"name":"Vector (Stroke)","rect":{"x":0,"y":0,"width":32,"height":32},"offset":{"x":0,"y":0},"originalSize":{"width":32,"height":32},"rotated":false,"capInsets":[0,0,0,0],"vertices":{"rawPosition":[-16,-16,0,16,-16,0,-16,16,0,16,16,0],"indexes":[0,1,2,2,1,3],"uv":[0,32,32,32,0,0,32,0],"nuv":[0,0,1,0,0,1,1,1],"minPos":{"x":-16,"y":-16,"z":0},"maxPos":{"x":16,"y":16,"z":0}},"packable":true,"pixelsToUnit":100,"pivot":{"x":0.5,"y":0.5},"meshType":0}],[0],0,[0],[2],[3]],[[{"name":"Group 1278","rect":{"x":1,"y":2,"width":123,"height":135},"offset":{"x":-0.5,"y":0},"originalSize":{"width":126,"height":139},"rotated":false,"capInsets":[0,0,0,0],"vertices":{"rawPosition":[-61.5,-67.5,0,61.5,-67.5,0,-61.5,67.5,0,61.5,67.5,0],"indexes":[0,1,2,2,1,3],"uv":[1,137,124,137,1,2,124,2],"nuv":[0.007936507936507936,0.014388489208633094,0.9841269841269841,0.014388489208633094,0.007936507936507936,0.9856115107913669,0.9841269841269841,0.9856115107913669],"minPos":{"x":-61.5,"y":-67.5,"z":0},"maxPos":{"x":61.5,"y":67.5,"z":0}},"packable":true,"pixelsToUnit":100,"pivot":{"x":0.5,"y":0.5},"meshType":0}],[0],0,[0],[2],[4]],[[[14,"SettingPopup"],[15,"SettingPopup",33554432,[-11,-12],[[2,-2,[0,"0aWI67vjtAC7zZ7KskHiHo"],[5,1920,1080]],[10,45,1920,1080,-3,[0,"a14/s75g9K+ryoLunZMc2r"]],[18,-10,[0,"6akyt3N7RMx5sdTaTmDt38"],-9,-8,-7,-6,-5,-4]],[1,"a2bIshmNZFCJS6kVklAudI",null,null,null,-1,0]],[5,"PopupBase",33554432,1,[-16,-17,-18,-19],[[2,-13,[0,"b2C2X/1zxFfINf+aSX1Kwx"],[5,754,467]],[19,0,-14,[0,"dbtnDxuiFCapKIi5GQL7g2"],9],[6,18,583,583,306.5,306.5,754,467,-15,[0,"3dkyVGJp1BqJVVovKXZgO9"]]],[1,"20EgFrYjhE/LFQlYndSz8p",null,null,null,1,0]],[5,"SFXNode",33554432,2,[-22,-23,-24],[[2,-20,[0,"55nBu992hAeYk+DX4ak0zo"],[5,1920,1080]],[6,45,-583,-583,-306.5,-306.5,1920,1080,-21,[0,"08gs0y+mhMOK+z/0Wzvdf8"]]],[1,"525s43ZdJHk5hYxbvjwIay",null,null,null,1,0]],[5,"BGMNode",33554432,2,[-27,-28,-29],[[2,-25,[0,"1eH7Ar4lJNIYb7BCPtaQNL"],[5,1920,1080]],[6,45,-583,-583,-306.5,-306.5,1920,1080,-26,[0,"16aes5VOJP0IIamAP8aYFa"]]],[1,"89aDtTSJhGZZ3Dt+HhINGS",null,null,null,1,0]],[16,"Overlay",33554432,1,[[2,-30,[0,"99qN/a26BCp4viaEhMlFOZ"],[5,1920,1080]],[20,1,0,-31,[0,"5erkPqMGNHKJebO0QDWSyE"],[4,2147483648],0],[10,45,1920,1080,-32,[0,"c8ieUZdzFM4pJyRs+gOIVl"]],[21,-33,[0,"92YGgh2xRIaqT4YvYnksYm"]]],[1,"3f3vG6O/hGz6jLnwL/FDTa",null,null,null,1,0]],[7,"ProgressBar",33554432,3,[-37],[[[2,-34,[0,"70YSI/EbtKuYnApw4Cy4rj"],[5,394,49]],[11,1,0,-35,[0,"96+WMnCGlJkY6NveQMxFbI"],3],-36],4,4,1],[1,"530LED+rRCEIO5WSq8LnwZ",null,null,null,1,0],[1,73.019,35.668,0]],[7,"ProgressBar",33554432,4,[-41],[[[2,-38,[0,"75EQshczFPtrU2Jxj5LmTi"],[5,394,49]],[11,1,0,-39,[0,"daoEi49eNN/YzDdxiYR2AM"],6],-40],4,4,1],[1,"b0IAPLbqhGurk2fgoOvKMp",null,null,null,1,0],[1,73.052,-113.943,0]],[3,"CloseButton",33554432,2,[[2,-42,[0,"3cXIxZcn5H9bmU89+sDPk/"],[5,32,32]],[4,-43,[0,"3eAM6GJndAoJ0h2vVhOmKD"],8],[22,3,-44,[0,"a9qIuEGShGy4TD1mObeZyu"],[[23,"97668z8Sv5GPp0DunWEXrPZ","onCloseClicked",1]]]],[1,"ccmnjaPQJBKqANTXXthZdM",null,null,null,1,0],[1,321.129,175.716,0]],[17,"HeadBase",33554432,2,[-47],[[2,-45,[0,"62hVpLuqhBXo/F3vs1eGBp"],[5,497,98]],[4,-46,[0,"616YgqkdpDn52xN2ol3Vnd"],1]],[1,"b9Rf46w51MRa8EX+Et0ZsP",null,null,null,1,0],[1,0,211.401,0]],[3,"Knob",33554432,3,[[2,-48,[0,"e4qwE/GgZHhZBU849KIoCY"],[5,74,79]],[4,-49,[0,"46Li43BXNG7YDXZpz193pk"],4]],[1,"58M9SRQY9EYomwcMD/QBk2",null,null,null,1,0],[1,-90,35.716,0]],[3,"Knob",33554432,4,[[2,-50,[0,"f2XZOcD3VK7YBqUM2uANjG"],[5,74,79]],[4,-51,[0,"b9YLcjqo5JdZx7Gr/9XE18"],7]],[1,"deCGGVHXROPrSBELoiSgWI",null,null,null,1,0],[1,-90,-114.321,0]],[3,"HeadText",33554432,9,[[2,-52,[0,"e516ocmR1NqZ/Li6KfSOLw"],[5,225,67]],[24,"Settings",50,50,50,1,true,1,true,-53,[0,"efgVKw9RRJYKdo26z6Ay+7"],[4,4278524018]]],[1,"37d51RCLNC4YFKd8r3zlsl",null,null,null,1,0],[1,0,1.864,0]],[3,"SfxLogo",33554432,3,[[2,-54,[0,"fd9EPvVedFv4ee48yD1u/u"],[5,123,135]],[4,-55,[0,"daBU3o9eBIn78+bAlUtGXi"],2]],[1,"ca6Ud5D3tCD5/Q8rw8/uNG",null,null,null,1,0],[1,-206.104,38.365,0]],[8,"Bar",33554432,6,[[[9,-56,[0,"949RYVZiZBx7EKE0kU96TY"],[5,394,49],[0,0,0.5]],-57],4,1],[1,"503b+h/D5PwY/Wi9Q+SkS2",null,null,null,1,0],[1,-197,0,0]],[3,"BGMLogo",33554432,4,[[2,-58,[0,"2bWdh84DZHYqdjzLTfOJvq"],[5,123,135]],[4,-59,[0,"7aF9xpvZRK05MQYY1j8U6y"],5]],[1,"26dybhCk5FsZ0cguSFd9Au",null,null,null,1,0],[1,-206.071,-111.246,0]],[8,"Bar",33554432,7,[[[9,-60,[0,"7dy7TQz9dHqZT2DlDHs3B/"],[5,394,49],[0,0,0.5]],-61],4,1],[1,"3b8rRhFmpCiaB5c9tdLBKQ",null,null,null,1,0],[1,-197,0,0]],[12,3,0,14,[0,"79yNdtsuZERr0SNVKwM86T"]],[13,2,0,6,[0,"136UZnGjZJHoMwEZhyh+Nx"],17],[12,3,0,16,[0,"6cJR66AUFAYbW326l3Qzsv"]],[13,2,0,7,[0,"e47TeGnflEHrPA4+bQf9Ze"],19]],0,[0,3,1,0,0,1,0,0,1,0,4,18,0,5,10,0,6,20,0,7,11,0,8,8,0,9,2,0,0,1,0,-1,5,0,-2,2,0,0,2,0,0,2,0,0,2,0,-1,9,0,-2,3,0,-3,4,0,-4,8,0,0,3,0,0,3,0,-1,13,0,-2,6,0,-3,10,0,0,4,0,0,4,0,-1,15,0,-2,7,0,-3,11,0,0,5,0,0,5,0,0,5,0,0,5,0,0,6,0,0,6,0,-3,18,0,-1,14,0,0,7,0,0,7,0,-3,20,0,-1,16,0,0,8,0,0,8,0,0,8,0,0,9,0,0,9,0,-1,12,0,0,10,0,0,10,0,0,11,0,0,11,0,0,12,0,0,12,0,0,13,0,0,13,0,0,14,0,-2,17,0,0,15,0,0,15,0,0,16,0,-2,19,0,10,1,61],[0,0,0,0,0,0,0,0,0,0,17,19],[1,1,1,1,1,1,1,1,1,1,1,1],[5,6,7,0,1,8,0,1,9,10,2,2]],[[{"name":"Rectangle 569","rect":{"x":0,"y":0,"width":394,"height":49},"offset":{"x":0,"y":0},"originalSize":{"width":394,"height":49},"rotated":false,"capInsets":[0,0,0,0],"vertices":{"rawPosition":[-197,-24.5,0,197,-24.5,0,-197,24.5,0,197,24.5,0],"indexes":[0,1,2,2,1,3],"uv":[0,49,394,49,0,0,394,0],"nuv":[0,0,1,0,0,1,1,1],"minPos":{"x":-197,"y":-24.5,"z":0},"maxPos":{"x":197,"y":24.5,"z":0}},"packable":true,"pixelsToUnit":100,"pivot":{"x":0.5,"y":0.5},"meshType":0}],[0],0,[0],[2],[11]],[[{"name":"Group 1138","rect":{"x":1,"y":0,"width":497,"height":98},"offset":{"x":-0.5,"y":1},"originalSize":{"width":500,"height":100},"rotated":false,"capInsets":[0,0,0,0],"vertices":{"rawPosition":[-248.5,-49,0,248.5,-49,0,-248.5,49,0,248.5,49,0],"indexes":[0,1,2,2,1,3],"uv":[1,100,498,100,1,2,498,2],"nuv":[0.002,0.02,0.996,0.02,0.002,1,0.996,1],"minPos":{"x":-248.5,"y":-49,"z":0},"maxPos":{"x":248.5,"y":49,"z":0}},"packable":true,"pixelsToUnit":100,"pivot":{"x":0.5,"y":0.5},"meshType":0}],[0],0,[0],[2],[12]],[[{"name":"Group 1137","rect":{"x":0,"y":0,"width":754,"height":467},"offset":{"x":0,"y":0},"originalSize":{"width":754,"height":467},"rotated":false,"capInsets":[0,0,0,0],"vertices":{"rawPosition":[-377,-233.5,0,377,-233.5,0,-377,233.5,0,377,233.5,0],"indexes":[0,1,2,2,1,3],"uv":[0,467,754,467,0,0,754,0],"nuv":[0,0,1,0,0,1,1,1],"minPos":{"x":-377,"y":-233.5,"z":0},"maxPos":{"x":377,"y":233.5,"z":0}},"packable":true,"pixelsToUnit":100,"pivot":{"x":0.5,"y":0.5},"meshType":0}],[0],0,[0],[2],[13]],[[{"name":"Group 1276","rect":{"x":1,"y":0,"width":74,"height":79},"offset":{"x":0,"y":1},"originalSize":{"width":76,"height":81},"rotated":false,"capInsets":[0,0,0,0],"vertices":{"rawPosition":[-37,-39.5,0,37,-39.5,0,-37,39.5,0,37,39.5,0],"indexes":[0,1,2,2,1,3],"uv":[1,81,75,81,1,2,75,2],"nuv":[0.013157894736842105,0.024691358024691357,0.9868421052631579,0.024691358024691357,0.013157894736842105,1,0.9868421052631579,1],"minPos":{"x":-37,"y":-39.5,"z":0},"maxPos":{"x":37,"y":39.5,"z":0}},"packable":true,"pixelsToUnit":100,"pivot":{"x":0.5,"y":0.5},"meshType":0}],[0],0,[0],[2],[14]],[[{"name":"Rectangle 571","rect":{"x":0,"y":0,"width":393,"height":49},"offset":{"x":0,"y":0},"originalSize":{"width":393,"height":49},"rotated":false,"capInsets":[0,0,0,0],"vertices":{"rawPosition":[-196.5,-24.5,0,196.5,-24.5,0,-196.5,24.5,0,196.5,24.5,0],"indexes":[0,1,2,2,1,3],"uv":[0,49,393,49,0,0,393,0],"nuv":[0,0,1,0,0,1,1,1],"minPos":{"x":-196.5,"y":-24.5,"z":0},"maxPos":{"x":196.5,"y":24.5,"z":0}},"packable":true,"pixelsToUnit":100,"pivot":{"x":0.5,"y":0.5},"meshType":0}],[0],0,[0],[2],[15]],[[{"name":"Group 1277","rect":{"x":1,"y":2,"width":123,"height":135},"offset":{"x":-0.5,"y":0},"originalSize":{"width":126,"height":139},"rotated":false,"capInsets":[0,0,0,0],"vertices":{"rawPosition":[-61.5,-67.5,0,61.5,-67.5,0,-61.5,67.5,0,61.5,67.5,0],"indexes":[0,1,2,2,1,3],"uv":[1,137,124,137,1,2,124,2],"nuv":[0.007936507936507936,0.014388489208633094,0.9841269841269841,0.014388489208633094,0.007936507936507936,0.9856115107913669,0.9841269841269841,0.9856115107913669],"minPos":{"x":-61.5,"y":-67.5,"z":0},"maxPos":{"x":61.5,"y":67.5,"z":0}},"packable":true,"pixelsToUnit":100,"pivot":{"x":0.5,"y":0.5},"meshType":0}],[0],0,[0],[2],[16]]]]
